just_prompt/__init__.py
just_prompt/__main__.py
just_prompt/server.py
just_prompt/atoms/__init__.py
just_prompt/atoms/llm_providers/__init__.py
just_prompt/atoms/llm_providers/anthropic.py
just_prompt/atoms/llm_providers/deepseek.py
just_prompt/atoms/llm_providers/gemini.py
just_prompt/atoms/llm_providers/groq.py
just_prompt/atoms/llm_providers/ollama.py
just_prompt/atoms/llm_providers/openai.py
just_prompt/atoms/shared/__init__.py
just_prompt/atoms/shared/data_types.py
just_prompt/atoms/shared/model_router.py
just_prompt/atoms/shared/utils.py
just_prompt/atoms/shared/validator.py
just_prompt/molecules/__init__.py
just_prompt/molecules/ceo_and_board_prompt.py
just_prompt/molecules/list_models.py
just_prompt/molecules/list_providers.py
just_prompt/molecules/prompt.py
just_prompt/molecules/prompt_from_file.py
just_prompt/molecules/prompt_from_file_to_file.py
just_prompt/tests/__init__.py
just_prompt/tests/atoms/__init__.py
just_prompt/tests/atoms/llm_providers/__init__.py
just_prompt/tests/atoms/llm_providers/test_anthropic.py
just_prompt/tests/atoms/llm_providers/test_deepseek.py
just_prompt/tests/atoms/llm_providers/test_gemini.py
just_prompt/tests/atoms/llm_providers/test_groq.py
just_prompt/tests/atoms/llm_providers/test_ollama.py
just_prompt/tests/atoms/llm_providers/test_openai.py
just_prompt/tests/atoms/shared/__init__.py
just_prompt/tests/atoms/shared/test_model_router.py
just_prompt/tests/atoms/shared/test_utils.py
just_prompt/tests/atoms/shared/test_validator.py
just_prompt/tests/molecules/__init__.py
just_prompt/tests/molecules/test_ceo_and_board_prompt.py
just_prompt/tests/molecules/test_list_models.py
just_prompt/tests/molecules/test_list_providers.py
just_prompt/tests/molecules/test_prompt.py
just_prompt/tests/molecules/test_prompt_from_file.py
just_prompt/tests/molecules/test_prompt_from_file_to_file.py
just_prompt-1.0.0.dist-info/licenses/LICENSE
just_prompt-1.0.0.dist-info/METADATA
just_prompt-1.0.0.dist-info/WHEEL
just_prompt-1.0.0.dist-info/entry_points.txt
just_prompt-1.0.0.dist-info/top_level.txt
just_prompt-1.0.0.dist-info/RECORD
