Metadata-Version: 2.4
Name: just-prompt
Version: 1.0.0
Summary: A lightweight MCP server for various LLM providers
Author-email: Jarad DeLorenzo <jarad@delorenj.com>
License: MIT
Project-URL: Homepage, https://delorenj.com
Project-URL: Repository, https://github.com/delorenj/just-prompt
Project-URL: Bug Tracker, https://github.com/delorenj/just-prompt/issues
Keywords: llm,mcp,ai,openai,anthropic,gemini,groq,deepseek,ollama
Classifier: Development Status :: 5 - Production/Stable
Classifier: Intended Audience :: Developers
Classifier: Programming Language :: Python :: 3
Classifier: Programming Language :: Python :: 3.10
Classifier: Programming Language :: Python :: 3.11
Classifier: Programming Language :: Python :: 3.12
Classifier: Topic :: Software Development :: Libraries :: Python Modules
Classifier: Topic :: Scientific/Engineering :: Artificial Intelligence
Requires-Python: >=3.10
License-File: LICENSE
Requires-Dist: anthropic>=0.49.0
Requires-Dist: google-genai>=1.11.0
Requires-Dist: groq>=0.20.0
Requires-Dist: ollama>=0.4.7
Requires-Dist: openai>=1.68.0
Requires-Dist: python-dotenv>=1.0.1
Requires-Dist: pydantic>=2.0.0
Requires-Dist: mcp>=0.1.5
Provides-Extra: test
Requires-Dist: pytest>=7.3.1; extra == "test"
Requires-Dist: pytest-asyncio>=0.20.3; extra == "test"
Dynamic: license-file
